Workbook
Name anos_investimento: Dashboard!$D$14
Name aporte: Dashboard!$D$13
Name patrimonio: Dashboard!$D$16
Name salario: Dashboard!$D$8
Name taxa_mensal: Dashboard!$D$15

Sheet Dashboard
A1: DIOInvest | Carteira de Investimento
B7: Carteira | F7: Projeções
B8: Salário | D8: 2000
B9: Sugestão de Investimento (30%) | D9: =salario*0.3 -> 600
B10: Taxa de Rendimento Mensal | D10: 0.006
B12: Investimento Mensal
B13: Valor Mensal | D13: 250
B14: Quantidade de Anos | D14: 5
B15: Taxa de Rendimento Mensal | D15: 0.0108
B16: Patrimônio Acumulado | D16: =FV(taxa_mensal,anos_investimento*12,aporte*-1) -> 20951.005
B17: Dividendos Mensais | D17: =patrimonio*taxa_mensal -> 226.27085
B19: Perfil | D19: Agressivo | F19: Fundos de Investimentos Imobiliários
B20: Aporte | D20: =D13 -> 250
B22: Tipo de FII | C22: Percentual Sugerido | D22: Valores
B23: Desenvolvimento | C23: =VLOOKUP($D$19&"-"&B23,FII!$B:$E,4,FALSE) -> 0.2 | D23: =C23*$D$20 -> 50
B24: FOFs | C24: =VLOOKUP($D$19&"-"&B24,FII!$B:$E,4,FALSE) -> 0.05 | D24: =C24*$D$20 -> 12.5
B25: Híbridos | C25: =VLOOKUP($D$19&"-"&B25,FII!$B:$E,4,FALSE) -> 0.05 | D25: =C25*$D$20 -> 12.5
B26: Hotelarias | C26: =VLOOKUP($D$19&"-"&B26,FII!$B:$E,4,FALSE) -> 0.1 | D26: =C26*$D$20 -> 25
B27: Papel | C27: =VLOOKUP($D$19&"-"&B27,FII!$B:$E,4,FALSE) -> 0.5 | D27: =C27*$D$20 -> 125
B28: Tijolo | C28: =VLOOKUP($D$19&"-"&B28,FII!$B:$E,4,FALSE) -> 0.1 | D28: =C28*$D$20 -> 25
D29: =SUM(D23:D28) -> 250

Sheet Cenários
B2: Projeção de Cenários | D2: Dividendo
B3: 1 ano | C3: =FV(Dashboard!$D$15,1*12,Dashboard!$D$13*-1) -> 3184.7738 | D3: =C3*Dashboard!$D$10 -> 19.108643
B4: 2 anos | C4: =FV(Dashboard!$D$15,2*12,Dashboard!$D$13*-1) -> 6807.7159 | D4: =C4*Dashboard!$D$10 -> 40.846295
B5: 3 anos | C5: =FV(Dashboard!$D$15,3*12,Dashboard!$D$13*-1) -> 10929.11 | D5: =C5*Dashboard!$D$10 -> 65.574663
B6: 5 anos | C6: =FV(Dashboard!$D$15,4*12,Dashboard!$D$13*-1) -> 15617.536 | D6: =C6*Dashboard!$D$10 -> 93.705214
B7: 7 anos | C7: =FV(Dashboard!$D$15,7*12,Dashboard!$D$13*-1) -> 33920.271 | D7: =C7*Dashboard!$D$10 -> 203.52163
B8: 10 anos | C8: =FV(Dashboard!$D$15,10*12,Dashboard!$D$13*-1) -> 60864.417 | D8: =C8*Dashboard!$D$10 -> 365.1865
B9: 12 anos | C9: =FV(Dashboard!$D$15,12*12,Dashboard!$D$13*-1) -> 85571.951 | D9: =C9*Dashboard!$D$10 -> 513.43171
B10: 15 anos | C10: =FV(Dashboard!$D$15,15*12,Dashboard!$D$13*-1) -> 136902.8 | D10: =C10*Dashboard!$D$10 -> 821.41677
B11: 18 anos | C11: =FV(Dashboard!$D$15,18*12,Dashboard!$D$13*-1) -> 212468.86 | D11: =C11*Dashboard!$D$10 -> 1274.8132
B12: 20 anos | C12: =FV(Dashboard!$D$15,20*12,Dashboard!$D$13*-1) -> 281762.25 | D12: =C12*Dashboard!$D$10 -> 1690.5735
B13: 25 anos | C13: =FV(Dashboard!$D$15,25*12,Dashboard!$D$13*-1) -> 557731.59 | D13: =C13*Dashboard!$D$10 -> 3346.3895
B14: 30 anos | C14: =FV(Dashboard!$D$15,30*12,Dashboard!$D$13*-1) -> 1083476.2 | D14: =C14*Dashboard!$D$10 -> 6500.8572
B15: 35 anos | C15: =FV(Dashboard!$D$15,35*12,Dashboard!$D$13*-1) -> 2085063.5 | D15: =C15*Dashboard!$D$10 -> 12510.381
B16: 40 anos | C16: =FV(Dashboard!$D$15,40*12,Dashboard!$D$13*-1) -> 3993171 | D16: =C16*Dashboard!$D$10 -> 23959.026
B17: 45 anos | C17: =FV(Dashboard!$D$15,45*12,Dashboard!$D$13*-1) -> 7628274.8 | D17: =C17*Dashboard!$D$10 -> 45769.649
B18: 50 anos | C18: =FV(Dashboard!$D$15,50*12,Dashboard!$D$13*-1) -> 14553451 | D18: =C18*Dashboard!$D$10 -> 87320.704

Sheet FII
B2: CHAVE | C2: PERFIL | D2: TIPO DE FII | E2: %
B3: =C3&"-"&D3 -> Conservador-Papel | C3: Conservador | D3: Papel | E3: 0.3
B4: =C4&"-"&D4 -> Conservador-Tijolo | C4: Conservador | D4: Tijolo | E4: 0.5
B5: =C5&"-"&D5 -> Conservador-Híbridos | C5: Conservador | D5: Híbridos | E5: 0.1
B6: =C6&"-"&D6 -> Conservador-FOFs | C6: Conservador | D6: FOFs | E6: 0.1
B7: =C7&"-"&D7 -> Conservador-Desenvolvimento | C7: Conservador | D7: Desenvolvimento | E7: 0
B8: =C8&"-"&D8 -> Conservador-Hotelarias | C8: Conservador | D8: Hotelarias | E8: 0
B9: =C9&"-"&D9 -> Moderado-Papel | C9: Moderado | D9: Papel | E9: 0.32
B10: =C10&"-"&D10 -> Moderado-Tijolo | C10: Moderado | D10: Tijolo | E10: 0.35
B11: =C11&"-"&D11 -> Moderado-Híbridos | C11: Moderado | D11: Híbridos | E11: 0.08
B12: =C12&"-"&D12 -> Moderado-FOFs | C12: Moderado | D12: FOFs | E12: 0.05
B13: =C13&"-"&D13 -> Moderado-Desenvolvimento | C13: Moderado | D13: Desenvolvimento | E13: 0.1
B14: =C14&"-"&D14 -> Moderado-Hotelarias | C14: Moderado | D14: Hotelarias | E14: 0.1
... B20: =C20&"-"&D20 -> Agressivo-Hotelarias | C20: Agressivo | D20: Hotelarias | E20: 0.1
